carsons/VERSION
carsons/__init__.py
carsons/carsons.py
carsons/py.typed
carsons-1.0.2.dist-info/licenses/LICENSE.txt
carsons-1.0.2.dist-info/METADATA
carsons-1.0.2.dist-info/WHEEL
carsons-1.0.2.dist-info/top_level.txt
carsons-1.0.2.dist-info/RECORD
