Metadata-Version: 2.4
Name: carsons
Version: 1.0.2
Summary: A python library computing carson's equations.
Author: Opus One Solutions
Author-email: rnd@opusonesolutions.com
License: copyright 2018 Opus One Solutions Energy Corporation
Project-URL: repository, https://github.com/opusonesolutions/carsons
Keywords: cables,carsons,energy,lines,power systems
Classifier: Development Status :: 3 - Alpha
Classifier: License :: OSI Approved :: MIT License
Classifier: Programming Language :: Python
Classifier: Programming Language :: Python :: 3 :: Only
Classifier: Programming Language :: Python :: 3.10
Classifier: Programming Language :: Python :: 3.11
Classifier: Programming Language :: Python :: 3.12
Classifier: Programming Language :: Python :: 3.13
Classifier: Topic :: Scientific/Engineering :: Mathematics
Classifier: Topic :: Scientific/Engineering :: Physics
Classifier: Topic :: Software Development :: Libraries :: Python Modules
Requires-Python: >=3.10
License-File: LICENSE.txt
Requires-Dist: numpy>=1.13.1
Provides-Extra: test
Requires-Dist: coverage>=7.8; extra == "test"
Requires-Dist: liccheck; extra == "test"
Requires-Dist: pint; extra == "test"
Requires-Dist: pre-commit; extra == "test"
Requires-Dist: pycobertura; extra == "test"
Requires-Dist: pytest>=3.6; extra == "test"
Requires-Dist: pytest-cov; extra == "test"
Requires-Dist: setuptools; extra == "test"
Dynamic: license-file
